[
    {
        "title" : "Nargileler",
        "image" : "menuphotos/1.jpg",
        "categorys" : [
            {
                "title" : "Yeni Trendler",
                "products" : [
                    {
                        "title" : "Dejavu",
                        "image" : "menuphotos/1.jpg",
                        "price" : "180 ₺"
                    },
                    {
                        "title" : "Plambir",
                        "image" : "menuphotos/1.jpg",
                        "price" : "180 ₺"
                    },
                    {
                        "title" : "Lady Killer",
                        "image" : "menuphotos/1.jpg",
                        "price" : "180 ₺"
                    },
                    {
                        "title" : "İzmir Romantik",
                        "image" : "menuphotos/1.jpg",
                        "price" : "180 ₺"
                    },
                    {
                        "title" : "Pişmiş Şeftali",
                        "image" : "menuphotos/1.jpg",
                        "price" : "180 ₺"
                    },
                    {
                        "title" : "Love 66",
                        "image" : "menuphotos/1.jpg",
                        "price" : "180 ₺"
                    }
                ]
            },
            {
                "title" : "Klasikler",
                "products" : [
                    {
                        "title" : "Çift Elma",
                        "image" : "menuphotos/1.jpg",
                        "price" : "190 ₺"
                    },
                    {
                        "title" : "Nakhla Elma",
                        "image" : "menuphotos/1.jpg",
                        "price" : "190 ₺"
                    },
                    {
                        "title" : "Yaban Mersini",
                        "image" : "menuphotos/1.jpg",
                        "price" : "190 ₺"
                    },
                    {
                        "title" : "Nakhla Cappuccino",
                        "image" : "menuphotos/1.jpg",
                        "price" : "190 ₺"
                    },
                    {
                        "title" : "Üzüm",
                        "image" : "menuphotos/1.jpg",
                        "price" : "190 ₺"
                    },
                    {
                        "title" : "Cappuccino",
                        "image" : "menuphotos/1.jpg",
                        "price" : "190 ₺"
                    }
                ]
            },
            {
                "title" : "Mix",
                "products" : [
                    {
                        "title" : "Üzüm Nane",
                        "image" : "menuphotos/1.jpg",
                        "price" : "195 ₺"
                    },
                    {
                        "title" : "Yaban Mersini Üzüm",
                        "image" : "menuphotos/1.jpg",
                        "price" : "195 ₺"
                    },
                    {
                        "title" : "Karpuz Çilek",
                        "image" : "menuphotos/1.jpg",
                        "price" : "195 ₺"
                    },
                    {
                        "title" : "Love 66 Pişmiş Şeftali",
                        "image" : "menuphotos/1.jpg",
                        "price" : "195 ₺"
                    },
                    {
                        "title" : "Limon Nane",
                        "image" : "menuphotos/1.jpg",
                        "price" : "195 ₺"
                    },
                    {
                        "title" : "Portakal Nane",
                        "image" : "menuphotos/1.jpg",
                        "price" : "195 ₺"
                    }
                ]
            },
            {
                "title" : "All Star",
                "products" : [
                    {
                        "title" : "Akdeniz",
                        "image" : "menuphotos/1.jpg",
                        "price" : "235 ₺"
                    },
                    {
                        "title" : "İstanbul",
                        "image" : "menuphotos/1.jpg",
                        "price" : "235 ₺"
                    },
                    {
                        "title" : "Code 69",
                        "image" : "menuphotos/1.jpg",
                        "price" : "235 ₺"
                    },
                    {
                        "title" : "Blue Mist",
                        "image" : "menuphotos/1.jpg",
                        "price" : "235 ₺"
                    },
                    {
                        "title" : "Magnum",
                        "image" : "menuphotos/1.jpg",
                        "price" : "235 ₺"
                    }
                ]
            }
        ]
    },
    {
        "title" : "Kahvaltılar",
        "image" : "menuphotos/2.jpg",
        "categorys" : [
            {
                "title" : "Kahvaltılar",
                "products" : [
                    {
                        "title" : "2 Kişilik Surname Yöresel Serpme Kahvaltı",
                        "image" : "menuphotos/2.jpg",
                        "price" : "485 ₺"
                    },
                    {
                        "title" : "1 Kişilik Surname Kahvaltı Tabağı",
                        "image" : "menuphotos/3.jpg",
                        "price" : "185 ₺"
                    },
                    {
                        "title" : "Muhlama",
                        "image" : "menuphotos/4.jpg",
                        "price" : "140 ₺"
                    }
                ]
            },
            {
                "title" : "Yumurtalar",
                "products" : [
                    {
                        "title" : "Sahanda Yumurta",
                        "image" : "menuphotos/5.jpg",
                        "price" : "65 ₺"
                    },
                    {
                        "title" : "Sahanda Kavurmalı Yumurta",
                        "image" : "menuphotos/6.jpg",
                        "price" : "130 ₺"
                    },
                    {
                        "title" : "Sahanda Sucuklu Yumurta",
                        "image" : "menuphotos/7.jpg",
                        "price" : "115 ₺"
                    },
                    {
                        "title" : "Sahanda Kaşarlı Yumurta",
                        "image" : "menuphotos/8.jpg",
                        "price" : "100 ₺"
                    },
                    {
                        "title" : "Sahanda Kaşarlı Sucuklu Yumurta",
                        "image" : "menuphotos/144.jpg",
                        "price" : "125 ₺"
                    },
                    {
                        "title" : "Sahanda Sucuk",
                        "image" : "menuphotos/9.jpg",
                        "price" : "100 ₺"
                    }
                    ,
                    {
                        "title" : "Izgara Hellim Peyniri",
                        "image" : "menuphotos/10.jpg",
                        "price" : "100 ₺"
                    }
                ]
            },
            {
                "title" : "Omletler",
                "products" : [
                    {
                        "title" : "Omlet",
                        "image" : "menuphotos/11.jpg",
                        "price" : "80 ₺"
                    },
                    {
                        "title" : "Kavurmalı Omlet",
                        "image" : "menuphotos/12.jpg",
                        "price" : "130 ₺"
                    },
                    {
                        "title" : "Kaşarlı Omlet",
                        "image" : "menuphotos/144.jpg",
                        "price" : "100 ₺"
                    },
                    {
                        "title" : "Sucuklu Omlet",
                        "image" : "menuphotos/13.jpg",
                        "price" : "115 ₺"
                    },
                    {
                        "title" : "Pastırmalı Omlet",
                        "image" : "menuphotos/14.jpg",
                        "price" : "140 ₺"
                    },
                    {
                        "title" : "Sebzeli Omlet",
                        "image" : "menuphotos/15.jpg",
                        "price" : "100 ₺"
                    }
                ]
            },
            {
                "title" : "Menemenler",
                "products" : [
                    {
                        "title" : "Menemen",
                        "image" : "menuphotos/144.jpg",
                        "price" : "105 ₺"
                    },
                    {
                        "title" : "Kaşarlı Menemen",
                        "image" : "menuphotos/16.jpg",
                        "price" : "120 ₺"
                    },
                    {
                        "title" : "Kaşarlı Sucuklu Menemen",
                        "image" : "menuphotos/17.jpg",
                        "price" : "135 ₺"
                    },
                    {
                        "title" : "Kavurmalı Menemen",
                        "image" : "menuphotos/18.jpg",
                        "price" : "155 ₺"
                    },
                    {
                        "title" : "Pastırmalı Menemen",
                        "image" : "menuphotos/144.jpg",
                        "price" : "155 ₺"
                    }
                ]
            },
            {
                "title" : "Gözlemeler",
                "products" : [
                    {
                        "title" : "Kaşarlı Gözleme",
                        "image" : "menuphotos/19.jpg",
                        "price" : "110 ₺"
                    },
                    {
                        "title" : "Beyaz Peynirli Gözleme",
                        "image" : "menuphotos/19.jpg",
                        "price" : "115 ₺"
                    },
                    {
                        "title" : "Kaşarlı Sucuklu Gözleme",
                        "image" : "menuphotos/20.jpg",
                        "price" : "125 ₺"
                    },
                    {
                        "title" : "Kavurmalı Kaşarlı Gözleme",
                        "image" : "menuphotos/19.jpg",
                        "price" : "135 ₺"
                    },
                    {
                        "title" : "Patatesli Gözleme",
                        "image" : "menuphotos/19.jpg",
                        "price" : "100 ₺"
                    }
                ]
            }
        ]
    },
    {
        "title" : "Tostlar",
        "image" : "menuphotos/21.jpg",
        "categorys" : [
            {
                "title" : "Tostlar",
                "products" : [
                    {
                        "title" : "Kaşarlı Tost",
                        "image" : "menuphotos/21.jpg",
                        "price" : "90 ₺"
                    },
                    {
                        "title" : "Surname Tost",
                        "image" : "menuphotos/21.jpg",
                        "price" : "100 ₺"
                    },
                    {
                        "title" : "Kavurmalı Kaşarlı Tost",
                        "image" : "menuphotos/21.jpg",
                        "price" : "135 ₺"
                    },
                    {
                        "title" : "Kaşarlı Sucuklu Tost",
                        "image" : "menuphotos/21.jpg",
                        "price" : "115 ₺"
                    },
                    {
                        "title" : "Pastırmalı Kaşarlı Tost",
                        "image" : "menuphotos/21.jpg",
                        "price" : "140 ₺"
                    }
                ]
            }
        ]
    },
    {
        "title" : "Atıştırmalıklar",
        "image" : "menuphotos/25.jpg",
        "categorys" : [
            {
                "title" : "Atıştırmalıklar",
                "products" : [
                    {
                        "title" : "Patates Tava",
                        "image" : "menuphotos/22.jpg",
                        "price" : "90 ₺"
                    },
                    {
                        "title" : "Elma Dilim Patates",
                        "image" : "menuphotos/23.jpg",
                        "price" : "90 ₺"
                    },
                    {
                        "title" : "Soğan Halkası",
                        "image" : "menuphotos/24.jpg",
                        "price" : "120 ₺"
                    },
                    {
                        "title" : "Sosis Sepeti",
                        "image" : "menuphotos/25.jpg",
                        "price" : "130 ₺"
                    },
                    {
                        "title" : "Paçanga Göreği",
                        "image" : "menuphotos/26.jpg",
                        "price" : "140 ₺"
                    },
                    {
                        "title" : "Sigara Böreği",
                        "image" : "menuphotos/27.jpg",
                        "price" : "120 ₺"
                    },
                    {
                        "title" : "Mozerella Sticks",
                        "image" : "menuphotos/28.jpg",
                        "price" : "130 ₺"
                    },
                    {
                        "title" : "Paneli Hellim",
                        "image" : "menuphotos/29.jpg",
                        "price" : "130 ₺"
                    },
                    {
                        "title" : "Atıştırma Tabağı",
                        "image" : "menuphotos/30.jpg",
                        "price" : "200 ₺"
                    },
                    {
                        "title" : "Çıtır Tavuk",
                        "image" : "menuphotos/144.jpg",
                        "price" : "180 ₺"
                    }
                ]
            }
        ]
    },
    {
        "title" : "Salatalar",
        "image" : "menuphotos/31.jpg",
        "categorys" : [
            {
                "title" : "Salatalar",
                "products" : [
                    {
                        "title" : "Izgara Hellim Salata",
                        "image" : "menuphotos/31.jpg",
                        "price" : "175 ₺"
                    },
                    {
                        "title" : "Tavuklu Sezar Salata",
                        "image" : "menuphotos/32.jpg",
                        "price" : "200 ₺"
                    },
                    {
                        "title" : "Ton Balıklı Salata",
                        "image" : "menuphotos/33.jpg",
                        "price" : "190 ₺"
                    },
                    {
                        "title" : "Çoban Salata",
                        "image" : "menuphotos/144.jpg",
                        "price" : "110 ₺"
                    }
                ]
            }
        ]
    },
    {
        "title" : "Burgerler, Quesadillas, Wraps",
        "image" : "menuphotos/37.jpg",
        "categorys" : [
            {
                "title" : "Burgerler",
                "products" : [
                    {
                        "title" : "Chihcken Burger",
                        "image" : "menuphotos/34.jpg",
                        "price" : "175 ₺"
                    },
                    {
                        "title" : "Surname Burger",
                        "image" : "menuphotos/35.jpg",
                        "price" : "200 ₺"
                    }
                ]
            },
            {
                "title" : "Quesadillas",
                "products" : [
                    {
                        "title" : "Etli Quesadilla",
                        "image" : "menuphotos/36.jpg",
                        "price" : "250 ₺"
                    },
                    {
                        "title" : "Tavuklu Quesadilla",
                        "image" : "menuphotos/36.jpg",
                        "price" : "200 ₺"
                    }
                ]
            },
            {
                "title" : "Wraps",
                "products" : [
                    {
                        "title" : "Etli Wrap",
                        "image" : "menuphotos/38.jpg",
                        "price" : "230 ₺"
                    },
                    {
                        "title" : "Tavuklu Wrap",
                        "image" : "menuphotos/38.jpg",
                        "price" : "200 ₺"
                    },
                    {
                        "title" : "Köfte Wrap",
                        "image" : "menuphotos/38.jpg",
                        "price" : "200 ₺"
                    }
                ]
            }
        ]
    },
    {
        "title" : "Makarnalar, Noodle's, Mantılar",
        "image" : "menuphotos/44.jpg",
        "categorys" : [
            {
                "title" : "Makarnalar",
                "products" : [
                    {
                        "title" : "Penne Napolitan",
                        "image" : "menuphotos/39.jpg",
                        "price" : "125 ₺"
                    },
                    {
                        "title" : "Penne Arabiata",
                        "image" : "menuphotos/39.jpg",
                        "price" : "130 ₺"
                    },
                    {
                        "title" : "Spaghetti Bolonez",
                        "image" : "menuphotos/40.jpg",
                        "price" : "170 ₺"
                    },
                    {
                        "title" : "Spaghetti Napolitan",
                        "image" : "menuphotos/40.jpg",
                        "price" : "125 ₺"
                    },
                    {
                        "title" : "Penne Beef",
                        "image" : "menuphotos/41.jpg",
                        "price" : "200 ₺"
                    },
                    {
                        "title" : "Fettucini Alfredo",
                        "image" : "menuphotos/42.jpg",
                        "price" : "180 ₺"
                    },{
                        "title" : "Fettucini Beef",
                        "image" : "menuphotos/42.jpg",
                        "price" : "200 ₺"
                    }
                ]
            },
            {
                "title" : "Noodle's",
                "products" : [
                    {
                        "title" : "Tavuklu Noodle",
                        "image" : "menuphotos/37.jpg",
                        "price" : "200 ₺"
                    },
                    {
                        "title" : "Etli Noodle",
                        "image" : "menuphotos/37.jpg",
                        "price" : "230 ₺"
                    },
                    {
                        "title" : "Sebzeli Noodle",
                        "image" : "menuphotos/37.jpg",
                        "price" : "160 ₺"
                    }
                ]
            },
            {
                "title" : "Mantılar",
                "products" : [
                    {
                        "title" : "Kayseri Mantısı",
                        "image" : "menuphotos/43.jpg",
                        "price" : "150 ₺"
                    },
                    {
                        "title" : "Kızarmış Mantı",
                        "image" : "menuphotos/44.jpg",
                        "price" : "160 ₺"
                    }
                ]
            }
        ]
    },
    {
        "title" : "Pizzalar",
        "image" : "menuphotos/52.jpg",
        "categorys" : [
            {
                "title" : "Pizzalar",
                "products" : [
                    {
                        "title" : "Quattro Formaggi Pizza",
                        "image" : "menuphotos/45.jpg",
                        "price" : "160 ₺"
                    },
                    {
                        "title" : "Alaturka Pizza",
                        "image" : "menuphotos/46.jpg",
                        "price" : "200 ₺"
                    },
                    {
                        "title" : "Chihcken Pizza",
                        "image" : "menuphotos/47.jpg",
                        "price" : "160 ₺"
                    },
                    {
                        "title" : "Margarita Pizza",
                        "image" : "menuphotos/48.jpg",
                        "price" : "150 ₺"
                    },
                    {
                        "title" : "Pizza Tonno",
                        "image" : "menuphotos/49.jpg",
                        "price" : "170 ₺"
                    },
                    {
                        "title" : "Fungi Pizza",
                        "image" : "menuphotos/50.jpg",
                        "price" : "160 ₺"
                    },
                    {
                        "title" : "Veggie Pizza",
                        "image" : "menuphotos/51.jpg",
                        "price" : "160 ₺"
                    },
                    {
                        "title" : "Meksika Pizza",
                        "image" : "menuphotos/52.jpg",
                        "price" : "210 ₺"
                    },
                    {
                        "title" : "Klasik Pizza",
                        "image" : "menuphotos/144.jpg",
                        "price" : "190 ₺"
                    }
                ]
            }
        ]
    },
    {
        "title" : "Yemekler",
        "image" : "menuphotos/59.jpg",
        "categorys" : [
            {
                "title" : "Et Yemekleri",
                "products" : [
                    {
                        "title" : "Surname Karışık Et Izgara",
                        "image" : "menuphotos/144.jpg",
                        "price" : "490 ₺"
                    },
                    {
                        "title" : "Surname Karışık Izgara",
                        "image" : "menuphotos/144.jpg",
                        "price" : "480 ₺"
                    },
                    {
                        "title" : "Kuzu Pirzola",
                        "image" : "menuphotos/53.jpg",
                        "price" : "430 ₺"
                    },
                    {
                        "title" : "1.5 Kuzu Pirzola",
                        "image" : "menuphotos/53.jpg",
                        "price" : "630 ₺"
                    },
                    {
                        "title" : "Tek Kalem Kuzu Pirzola",
                        "image" : "menuphotos/53.jpg",
                        "price" : "160 ₺"
                    },
                    {
                        "title" : "Kuzu Lokum",
                        "image" : "menuphotos/54.jpg",
                        "price" : "330 ₺"
                    },
                    {
                        "title" : "1.5 Kuzu Lokum",
                        "image" : "menuphotos/54.jpg",
                        "price" : "490 ₺"
                    },
                    {
                        "title" : "Izgara Köfte",
                        "image" : "menuphotos/55.jpg",
                        "price" : "190 ₺"
                    },
                    {
                        "title" : "1.5 Izgara Köfte",
                        "image" : "menuphotos/55.jpg",
                        "price" : "275 ₺"
                    },
                    {
                        "title" : "Acılı Köfte",
                        "image" : "menuphotos/55.jpg",
                        "price" : "190 ₺"
                    },
                    {
                        "title" : "1.5 Acılı Köfte",
                        "image" : "menuphotos/55.jpg",
                        "price" : "275 ₺"
                    },
                    {
                        "title" : "Kaşarlı Köfte",
                        "image" : "menuphotos/56.jpg",
                        "price" : "230 ₺"
                    },
                    {
                        "title" : "1.5 Kaşarlı Köfte",
                        "image" : "menuphotos/56.jpg",
                        "price" : "310 ₺"
                    },
                    {
                        "title" : "Tek Kalem Kaşarlı Köfte",
                        "image" : "menuphotos/56.jpg",
                        "price" : "100 ₺"
                    },
                    {
                        "title" : "Karışık Köfte",
                        "image" : "menuphotos/57.jpg",
                        "price" : "275 ₺"
                    },
                    {
                        "title" : "Çökertme",
                        "image" : "menuphotos/58.jpg",
                        "price" : "340 ₺"
                    },
                    {
                        "title" : "Et Fajita",
                        "image" : "menuphotos/144.jpg",
                        "price" : "340 ₺"
                    },
                    {
                        "title" : "Comba Fajita",
                        "image" : "menuphotos/59.jpg",
                        "price" : "340 ₺"
                    },
                    {
                        "title" : "Izgara Antrikot",
                        "image" : "menuphotos/144.jpg",
                        "price" : "340 ₺"
                    },
                    {
                        "title" : "Cheddar Peynirli Dana Sosis",
                        "image" : "menuphotos/144.jpg",
                        "price" : "190 ₺"
                    },
                    {
                        "title" : "Izgara Dana Sucuk",
                        "image" : "menuphotos/144.jpg",
                        "price" : "190 ₺"
                    }
                ]
            },
            {
                "title" : "Tavuk Yemekleri",
                "products" : [
                    {
                        "title" : "Izgara Tavuk Bonfile",
                        "image" : "menuphotos/60.jpg",
                        "price" : "180 ₺"
                    },
                    {
                        "title" : "1.5 Izgara Tavuk Bonfile",
                        "image" : "menuphotos/60.jpg",
                        "price" : "240 ₺"
                    },
                    {
                        "title" : "Izgara Tavuk Pirzola",
                        "image" : "menuphotos/61.jpg",
                        "price" : "190 ₺"
                    },
                    {
                        "title" : "1.5 Izgara Tavuk Pirzola",
                        "image" : "menuphotos/61.jpg",
                        "price" : "260 ₺"
                    },
                    {
                        "title" : "Köri Soslu Tavuk",
                        "image" : "menuphotos/144.jpg",
                        "price" : "180 ₺"
                    },
                    {
                        "title" : "Barbekü Soslu Tavuk",
                        "image" : "menuphotos/144.jpg",
                        "price" : "180 ₺"
                    },
                    {
                        "title" : "Meksika Soslu Tavuk",
                        "image" : "menuphotos/144.jpg",
                        "price" : "180 ₺"
                    },
                    {
                        "title" : "Tavuk Fajita",
                        "image" : "menuphotos/144.jpg",
                        "price" : "260 ₺"
                    },
                    {
                        "title" : "Yaprak Kanay",
                        "image" : "menuphotos/145.jpg",
                        "price" : "190 ₺"
                    },
                    {
                        "title" : "Tavuk Şiş",
                        "image" : "menuphotos/144.jpg",
                        "price" : "180 ₺"
                    }
                ]
            },
            {
                "title" : "Pilavlar",
                "products" : [
                    {
                        "title" : "Bulgur Pilavı",
                        "image" : "menuphotos/144.jpg",
                        "price" : "40 ₺"
                    },
                    {
                        "title" : "Pirinç Pilavı",
                        "image" : "menuphotos/144.jpg",
                        "price" : "40 ₺"
                    }
                ]
            }
        ]
    },
    {
        "title" : "Tatlılar",
        "image" : "menuphotos/76.jpg",
        "categorys" : [
            {
                "title" : "Tatlılar",
                "products" : [
                    {
                        "title" : "Çiroz",
                        "image" : "menuphotos/62.jpg",
                        "price" : "85  ₺"
                    },
                    {
                        "title" : "Meyveli Çiroz",
                        "image" : "menuphotos/63.jpg",
                        "price" : "110 ₺"
                    },
                    {
                        "title" : "Sütlü Kadayıf",
                        "image" : "menuphotos/64.jpg",
                        "price" : "105 ₺"
                    },
                    {
                        "title" : "Künefe",
                        "image" : "menuphotos/144.jpg",
                        "price" : "110 ₺"
                    },
                    {
                        "title" : "Katmer",
                        "image" : "menuphotos/65.jpg",
                        "price" : "120 ₺"
                    },
                    {
                        "title" : "San Sebastian Cheesecake",
                        "image" : "menuphotos/66.jpg",
                        "price" : "110 ₺"
                    },
                    {
                        "title" : "Vişneli Beyaz Brownie",
                        "image" : "menuphotos/67.jpg",
                        "price" : "130 ₺"
                    },
                    {
                        "title" : "Çerez Tabağı",
                        "image" : "menuphotos/68.jpg",
                        "price" : "80 ₺"
                    },
                    {
                        "title" : "Trileçe",
                        "image" : "menuphotos/69.jpg",
                        "price" : "80 ₺"
                    },
                    {
                        "title" : "Soğuk Baklava",
                        "image" : "menuphotos/70.jpg",
                        "price" : "85 ₺"
                    },
                    {
                        "title" : "Yer Fıstıklı Karamelli Pasta",
                        "image" : "menuphotos/71.jpg",
                        "price" : "110 ₺"
                    },
                    {
                        "title" : "Sütlaç",
                        "image" : "menuphotos/72.jpg",
                        "price" : "75 ₺"
                    },
                    {
                        "title" : "Limonlu Cheesecake",
                        "image" : "menuphotos/73.jpg",
                        "price" : "110 ₺"
                    },
                    {
                        "title" : "Tiramisu",
                        "image" : "menuphotos/74.jpg",
                        "price" : "120 ₺"
                    },
                    {
                        "title" : "Mono Latte Pasta",
                        "image" : "menuphotos/75.jpg",
                        "price" : "110 ₺"
                    },
                    {
                        "title" : "Frambuazlı Cheesecake",
                        "image" : "menuphotos/76.jpg",
                        "price" : "110 ₺"
                    },
                    {
                        "title" : "Kaymaklı Rende Kabak",
                        "image" : "menuphotos/77.jpg",
                        "price" : "140 ₺"
                    },
                    {
                        "title" : "Suffle",
                        "image" : "menuphotos/78.jpg",
                        "price" : "140 ₺"
                    },
                    {
                        "title" : "Sıcak Brownie",
                        "image" : "menuphotos/79.jpg",
                        "price" : "135 ₺"
                    },
                    {
                        "title" : "Fıstık Rüyası",
                        "image" : "menuphotos/80.jpg",
                        "price" : "115 ₺"
                    },
                    {
                        "title" : "Frambuazlı Kalpli Pasta",
                        "image" : "menuphotos/81.jpg",
                        "price" : "210 ₺"
                    },
                    {
                        "title" : "Frambuazlı Çikolatalı Kek",
                        "image" : "menuphotos/82.jpg",
                        "price" : "200 ₺"
                    },
                    {
                        "title" : "Profiterollü Pasta",
                        "image" : "menuphotos/83.jpg",
                        "price" : "120 ₺"
                    },
                    {
                        "title" : "Kırmızı Kalpli Pasta",
                        "image" : "menuphotos/84.jpg",
                        "price" : "150 ₺"
                    }
                ]
            }
        ]
    },
    {
        "title" : "İçecekler",
        "image" : "menuphotos/143.jpg",
        "categorys" : [
            {
                "title" : "Sotf İçecekler",
                "products" : [
                    {
                        "title" : "Niğde Gazozu",
                        "image" : "menuphotos/85.jpg",
                        "price" : "40 ₺"
                    },
                    {
                        "title" : "Elmalı Soda",
                        "image" : "menuphotos/86.jpg",
                        "price" : "30 ₺"
                    },
                    {
                        "title" : "Vişneli Soda",
                        "image" : "menuphotos/87.jpg",
                        "price" : "30 ₺"
                    },
                    {
                        "title" : "Çilekli Soda",
                        "image" : "menuphotos/88.jpg",
                        "price" : "30 ₺"
                    },
                    {
                        "title" : "Pepsi",
                        "image" : "menuphotos/89.jpg",
                        "price" : "40 ₺"
                    },
                    {
                        "title" : "Pepsi Max",
                        "image" : "menuphotos/90.jpg",
                        "price" : "40 ₺"
                    },
                    {
                        "title" : "Yedigün",
                        "image" : "menuphotos/91.jpg",
                        "price" : "40 ₺"
                    },
                    {
                        "title" : "Lipton Ice Tea Mango",
                        "image" : "menuphotos/92.jpg",
                        "price" : "40 ₺"
                    },
                    {
                        "title" : "Lipton Ice Tea Şeftali",
                        "image" : "menuphotos/93.jpg",
                        "price" : "40 ₺"
                    },
                    {
                        "title" : "Lipton Ice Tea Limon",
                        "image" : "menuphotos/94.jpg",
                        "price" : "40 ₺"
                    },
                    {
                        "title" : "Fruko Cool Lime",
                        "image" : "menuphotos/95.jpg",
                        "price" : "40 ₺"
                    },
                    {
                        "title" : "Redbull",
                        "image" : "menuphotos/96.jpg",
                        "price" : "75 ₺"
                    },
                    {
                        "title" : "Seven Up Gazoz",
                        "image" : "menuphotos/97.jpg",
                        "price" : "40 ₺"
                    },
                    {
                        "title" : "Cam Su",
                        "image" : "menuphotos/98.jpg",
                        "price" : "15 ₺"
                    },
                    {
                        "title" : "Pet Su",
                        "image" : "menuphotos/99.jpg",
                        "price" : "10 ₺"
                    },
                    {
                        "title" : "Maden Suyu",
                        "image" : "menuphotos/100.jpg",
                        "price" : "25 ₺"
                    },
                    {
                        "title" : "San Pellegrino",
                        "image" : "menuphotos/101.jpg",
                        "price" : "25 ₺"
                    },
                    {
                        "title" : "Sıkma Limonlu Maden Suyu",
                        "image" : "menuphotos/102.jpg",
                        "price" : "30 ₺"
                    },
                    {
                        "title" : "Tropicana Karışık Meyve Suyu",
                        "image" : "menuphotos/103.jpg",
                        "price" : "40 ₺"
                    },
                    {
                        "title" : "Tropicana Şeftali Meyve Suyu",
                        "image" : "menuphotos/105.jpg",
                        "price" : "40 ₺"
                    },
                    {
                        "title" : "Tropicana Vişne Meyve Suyu",
                        "image" : "menuphotos/106.jpg",
                        "price" : "40 ₺"
                    },
                    {
                        "title" : "Cappy Kayısı Meyve Burger",
                        "image" : "menuphotos/104.jpg",
                        "price" : "40 ₺"
                    },
                    {
                        "title" : "Ayran",
                        "image" : "menuphotos/107.jpg",
                        "price" : "35 ₺"
                    },
                    {
                        "title" : "Naneli Ayran",
                        "image" : "menuphotos/107.jpg",
                        "price" : "36 ₺"
                    },
                    {
                        "title" : "Fesleğenli Ayran",
                        "image" : "menuphotos/107.jpg",
                        "price" : "36 ₺"
                    }
                ]
            },
            {
                "title" : "Türk Kahveleri",
                "products" : [
                    {
                        "title" : "Klasik Türk Kahvesi",
                        "image" : "menuphotos/110.jpg",
                        "price" : "45 ₺"
                    },
                    {
                        "title" : "Double Türk Kahvesi",
                        "image" : "menuphotos/110.jpg",
                        "price" : "65 ₺"
                    },
                    {
                        "title" : "Damla Sakızlı Türk Kahvesi",
                        "image" : "menuphotos/110.jpg",
                        "price" : "45 ₺"
                    },
                    {
                        "title" : "Dibek Kahvevsi",
                        "image" : "menuphotos/110.jpg",
                        "price" : "45 ₺"
                    },
                    {
                        "title" : "Menengiç Kahvesi",
                        "image" : "menuphotos/110.jpg",
                        "price" : "45 ₺"
                    },
                    {
                        "title" : "Sütlü Türk Kahvesi",
                        "image" : "menuphotos/110.jpg",
                        "price" : "45 ₺"
                    },
                    {
                        "title" : "Dağ Çilekli Türk Kahvesi",
                        "image" : "menuphotos/110.jpg",
                        "price" : "45 ₺"
                    },
                    {
                        "title" : "Çikolatalı Türk Kahvesi",
                        "image" : "menuphotos/110.jpg",
                        "price" : "45 ₺"
                    },
                    {
                        "title" : "Beyaz Çikolatalı Türk Kahvesi",
                        "image" : "menuphotos/110.jpg",
                        "price" : "45 ₺"
                    }
                ]
            },
            {
                "title" : "Sıcak İçecekler",
                "products" : [
                    {
                        "title" : "Ruby Çikolata",
                        "image" : "menuphotos/144.jpg",
                        "price" : "55 ₺"
                    },
                    {
                        "title" : "Gripin",
                        "image" : "menuphotos/144.jpg",
                        "price" : "55 ₺"
                    },
                    {
                        "title" : "Sütlü Çay",
                        "image" : "menuphotos/144.jpg",
                        "price" : "30 ₺"
                    },
                    {
                        "title" : "Aromalı Sıcak Çikolata",
                        "image" : "menuphotos/144.jpg",
                        "price" : "50 ₺"
                    },
                    {
                        "title" : "Çay",
                        "image" : "menuphotos/111.jpg",
                        "price" : "15 ₺"
                    },
                    {
                        "title" : "Fincan Çay",
                        "image" : "menuphotos/112.jpg",
                        "price" : "25 ₺"
                    },
                    {
                        "title" : "Sıcak Çikolata",
                        "image" : "menuphotos/113.jpg",
                        "price" : "65 ₺"
                    },
                    {
                        "title" : "Sıcak Beyaz Çikolata",
                        "image" : "menuphotos/113.jpg",
                        "price" : "55 ₺"
                    },
                    {
                        "title" : "Sıcak Süt",
                        "image" : "menuphotos/114.jpg",
                        "price" : "25 ₺"
                    },
                    {
                        "title" : "Matcha Latte",
                        "image" : "menuphotos/115.jpg",
                        "price" : "45 ₺"
                    },
                    {
                        "title" : "Matcha Çayı",
                        "image" : "menuphotos/115.jpg",
                        "price" : "45 ₺"
                    },
                    {
                        "title" : "Salep",
                        "image" : "menuphotos/116.jpg",
                        "price" : "65 ₺"
                    },
                    {
                        "title" : "Chai Tea Latte",
                        "image" : "menuphotos/116.jpg",
                        "price" : "45 ₺"
                    }
                ]
            },
            {
                "title" : "Çekirdek Kahveler",
                "products" : [
                    {
                        "title" : "Cappuccino",
                        "image" : "menuphotos/117.jpg",
                        "price" : "60 ₺"
                    },
                    {
                        "title" : "Mocha",
                        "image" : "menuphotos/118.jpg",
                        "price" : "60 ₺"
                    },
                    {
                        "title" : "White Mocha",
                        "image" : "menuphotos/118.jpg",
                        "price" : "60 ₺"
                    },
                    {
                        "title" : "Instant",
                        "image" : "menuphotos/119.jpg",
                        "price" : "55 ₺"
                    },
                    {
                        "title" : "Espresso Machiato",
                        "image" : "menuphotos/120.jpg",
                        "price" : "55 ₺"
                    },
                    {
                        "title" : "Cafe Latte",
                        "image" : "menuphotos/121.jpg",
                        "price" : "60 ₺"
                    },
                    {
                        "title" : "Americano",
                        "image" : "menuphotos/144.jpg",
                        "price" : "65 ₺"
                    },
                    {
                        "title" : "Espresso",
                        "image" : "menuphotos/144.jpg",
                        "price" : "50 ₺"
                    },
                    {
                        "title" : "Double Espresso",
                        "image" : "menuphotos/144.jpg",
                        "price" : "75 ₺"
                    },
                    {
                        "title" : "Zebra Mocha",
                        "image" : "menuphotos/144.jpg",
                        "price" : "60 ₺"
                    },
                    {
                        "title" : "Balkabaklı Latte",
                        "image" : "menuphotos/144.jpg",
                        "price" : "60 ₺"
                    },
                    {
                        "title" : "Caramel Macchiato",
                        "image" : "menuphotos/144.jpg",
                        "price" : "60 ₺"
                    },
                    {
                        "title" : "Aromalı Latte",
                        "image" : "menuphotos/144.jpg",
                        "price" : "60 ₺"
                    },
                    {
                        "title" : "Caramel Mocha",
                        "image" : "menuphotos/144.jpg",
                        "price" : "60 ₺"
                    },
                    {
                        "title" : "Instant Sütlü",
                        "image" : "menuphotos/144.jpg",
                        "price" : "60 ₺"
                    },
                    {
                        "title" : "Pot Süt",
                        "image" : "menuphotos/144.jpg",
                        "price" : "10 ₺"
                    }
                ]
            },
            {
                "title" : "Smoothie's",
                "products" : [
                    {
                        "title" : "Çilek-Nane Smoothie",
                        "image" : "menuphotos/122.jpg",
                        "price" : "85 ₺"
                    },
                    {
                        "title" : "Vanilya-Şeftali Smoothie",
                        "image" : "menuphotos/123.jpg",
                        "price" : "85 ₺"
                    }
                ]
            },
            {
                "title" : "Limonatalar",
                "products" : [
                    {
                        "title" : "Klasik Limonata",
                        "image" : "menuphotos/124.jpg",
                        "price" : "60 ₺"
                    },
                    {
                        "title" : "Naneli Limonata",
                        "image" : "menuphotos/124.jpg",
                        "price" : "65 ₺"
                    },
                    {
                        "title" : "Çilekli Linonata",
                        "image" : "menuphotos/124.jpg",
                        "price" : "65 ₺"
                    },
                    {
                        "title" : "Matcha Limonata",
                        "image" : "menuphotos/124.jpg",
                        "price" : "65 ₺"
                    },
                    {
                        "title" : "Yaban Mersinli Limonata",
                        "image" : "menuphotos/124.jpg",
                        "price" : "65 ₺"
                    },
                    {
                        "title" : "Orman Meyveli Limonata",
                        "image" : "menuphotos/124.jpg",
                        "price" : "65 ₺"
                    }
                ]
            },
            {
                "title" : "Alternatif Soğuklar",
                "products" : [
                    {
                        "title" : "Ev Yapımı Soğuk Çay - Limon",
                        "image" : "menuphotos/125.jpg",
                        "price" : "60 ₺"
                    },
                    {
                        "title" : "Ev Yapımı Soğuk Çay - Mango",
                        "image" : "menuphotos/125.jpg",
                        "price" : "60 ₺"
                    },
                    {
                        "title" : "Ev Yapımı Soğuk Çay - Şeftali",
                        "image" : "menuphotos/125.jpg",
                        "price" : "60 ₺"
                    },
                    {
                        "title" : "Taze Sıkım Portakal Suyu",
                        "image" : "menuphotos/144.jpg",
                        "price" : "60 ₺"
                    },
                    {
                        "title" : "Soğuk Bisküvili Salep",
                        "image" : "menuphotos/126.jpg",
                        "price" : "65 ₺"
                    },
                    {
                        "title" : "Cocoberry",
                        "image" : "menuphotos/126.jpg",
                        "price" : "65 ₺"
                    },
                    {
                        "title" : "C-Mix",
                        "image" : "menuphotos/144.jpg",
                        "price" : "65 ₺"
                    },
                    {
                        "title" : "Soğuk Matcha Çayı",
                        "image" : "menuphotos/144.jpg",
                        "price" : "60 ₺"
                    },
                    {
                        "title" : "Soğuk Chai Tea",
                        "image" : "menuphotos/144.jpg",
                        "price" : "60 ₺"
                    },
                    {
                        "title" : "Soğuk Beyaz Çikolata",
                        "image" : "menuphotos/144.jpg",
                        "price" : "65 ₺"
                    },
                    {
                        "title" : "Soğuk Çikolata",
                        "image" : "menuphotos/144.jpg",
                        "price" : "65 ₺"
                    }
                ]
            },
            {
                "title" : "Milkshake's",
                "products" : [
                    {
                        "title" : "Çilekli Milkshake",
                        "image" : "menuphotos/127.jpg",
                        "price" : "80 ₺"
                    },
                    {
                        "title" : "Vanilyalı Milkshake",
                        "image" : "menuphotos/128.jpg",
                        "price" : "80 ₺"
                    },
                    {
                        "title" : "Kinder Milkshake",
                        "image" : "menuphotos/128.jpg",
                        "price" : "80 ₺"
                    },
                    {
                        "title" : "Çikolatalı Milkshake",
                        "image" : "menuphotos/128.jpg",
                        "price" : "80 ₺"
                    },
                    {
                        "title" : "Protein Shake",
                        "image" : "menuphotos/128.jpg",
                        "price" : "80 ₺"
                    },
                    {
                        "title" : "Lotus Milkshake",
                        "image" : "menuphotos/128.jpg",
                        "price" : "80 ₺"
                    },
                    {
                        "title" : "Oreolu Milkshake",
                        "image" : "menuphotos/128.jpg",
                        "price" : "80 ₺"
                    }
                ]
            },
            {
                "title" : "Soğuk Kahveler",
                "products" : [
                    {
                        "title" : "Buzlu Latte",
                        "image" : "menuphotos/129.jpg",
                        "price" : "70 ₺"
                    },
                    {
                        "title" : "Soğuk Matcha Latte",
                        "image" : "menuphotos/118.jpg",
                        "price" : "70 ₺"
                    },
                    {
                        "title" : "Buzlu Americana",
                        "image" : "menuphotos/130.jpg",
                        "price" : "70 ₺"
                    },
                    {
                        "title" : "Affogato",
                        "image" : "menuphotos/131.jpg",
                        "price" : "70 ₺"
                    },
                    {
                        "title" : "Buzlu Beyaz Mocha",
                        "image" : "menuphotos/144.jpg",
                        "price" : "70 ₺"
                    },
                    {
                        "title" : "Buzlu Mocha",
                        "image" : "menuphotos/144.jpg",
                        "price" : "70 ₺"
                    },
                    {
                        "title" : "Frappuccino",
                        "image" : "menuphotos/132.jpg",
                        "price" : "70 ₺"
                    },
                    {
                        "title" : "Frappe",
                        "image" : "menuphotos/133.jpg",
                        "price" : "70 ₺"
                    }
                ]
            },
            {
                "title" : "Filtre Kahveler ve Yöresel Kahveler",
                "products" : [
                    {
                        "title" : "Decaf Filtre Kahve",
                        "image" : "menuphotos/135.jpg",
                        "price" : "60 ₺"
                    },
                    {
                        "title" : "Colombia, Guatemele, Brazil, Ethiopia",
                        "image" : "menuphotos/136.jpg",
                        "price" : "65 ₺"
                    },
                    {
                        "title" : "Klasik Filtre Kahve",
                        "image" : "menuphotos/136.jpg",
                        "price" : "65 ₺"
                    },
                    {
                        "title" : "French Karamel",
                        "image" : "menuphotos/144.jpg",
                        "price" : "60 ₺"
                    },
                    {
                        "title" : "French Vanilya",
                        "image" : "menuphotos/144.jpg",
                        "price" : "60 ₺"
                    }
                ]
            },
            {
                "title" : "Frozen's",
                "products" : [
                    {
                        "title" : "kırmızı Orman Frozen",
                        "image" : "menuphotos/136.jpg",
                        "price" : "75 ₺"
                    },
                    {
                        "title" : "Limon Frozen",
                        "image" : "menuphotos/136.jpg",
                        "price" : "75 ₺"
                    },
                    {
                        "title" : "Karadut Frozen",
                        "image" : "menuphotos/136.jpg",
                        "price" : "75 ₺"
                    },
                    {
                        "title" : "Mango Frozen",
                        "image" : "menuphotos/136.jpg",
                        "price" : "75 ₺"
                    },
                    {
                        "title" : "Ananas Frozen",
                        "image" : "menuphotos/136.jpg",
                        "price" : "75 ₺"
                    },
                    {
                        "title" : "Çilekli Frozen",
                        "image" : "menuphotos/136.jpg",
                        "price" : "75 ₺"
                    },
                    {
                        "title" : "Karpuz - Çilek Frozen",
                        "image" : "menuphotos/136.jpg",
                        "price" : "75 ₺"
                    }
                ]
            },
            {
                "title" : "Alkolsüz Kokteyller",
                "products" : [
                    {
                        "title" : "Mojito",
                        "image" : "menuphotos/144.jpg",
                        "price" : "70 ₺"
                    },
                    {
                        "title" : "Mojito - Elma",
                        "image" : "menuphotos/137.jpg",
                        "price" : "75 ₺"
                    },
                    {
                        "title" : "Mojito - Çilek",
                        "image" : "menuphotos/138.jpg",
                        "price" : "75 ₺"
                    },
                    {
                        "title" : "Banana's Mango",
                        "image" : "menuphotos/138.jpg",
                        "price" : "75 ₺"
                    },
                    {
                        "title" : "Red Line",
                        "image" : "menuphotos/139.jpg",
                        "price" : "80 ₺"
                    },
                    {
                        "title" : "Pineapple Sush",
                        "image" : "menuphotos/139.jpg",
                        "price" : "105 ₺"
                    },
                    {
                        "title" : "Churcill",
                        "image" : "menuphotos/144.jpg",
                        "price" : "35 ₺"
                    }
                ]
            },
            {
                "title" : "Meyve ve Bitki Çayları",
                "products" : [
                    {
                        "title" : "Melisa Çayı",
                        "image" : "menuphotos/144.jpg",
                        "price" : "50 ₺"
                    },
                    {
                        "title" : "Ada Çayı",
                        "image" : "menuphotos/144.jpg",
                        "price" : "50 ₺"
                    },
                    {
                        "title" : "Yeşil Çay",
                        "image" : "menuphotos/144.jpg",
                        "price" : "50 ₺"
                    },
                    {
                        "title" : "Kış Çayı",
                        "image" : "menuphotos/144.jpg",
                        "price" : "50 ₺"
                    },
                    {
                        "title" : "Berry Love Tea",
                        "image" : "menuphotos/144.jpg",
                        "price" : "50 ₺"
                    },
                    {
                        "title" : "Nane Limon Çayı",
                        "image" : "menuphotos/144.jpg",
                        "price" : "50 ₺"
                    },
                    {
                        "title" : "Kuşburnu",
                        "image" : "menuphotos/144.jpg",
                        "price" : "50 ₺"
                    },
                    {
                        "title" : "Ihlamur",
                        "image" : "menuphotos/144.jpg",
                        "price" : "50 ₺"
                    },
                    {
                        "title" : "Kırmızı Orman Meyveli Çay",
                        "image" : "menuphotos/144.jpg",
                        "price" : "50 ₺"
                    },
                    {
                        "title" : "Papatya Çayı",
                        "image" : "menuphotos/144.jpg",
                        "price" : "50 ₺"
                    },
                    {
                        "title" : "Elma Çayı",
                        "image" : "menuphotos/144.jpg",
                        "price" : "50 ₺"
                    },
                    {
                        "title" : "Relax Çayı",
                        "image" : "menuphotos/144.jpg",
                        "price" : "50 ₺"
                    },
                    {
                        "title" : "Fas Çayı",
                        "image" : "menuphotos/144.jpg",
                        "price" : "50 ₺"
                    }
                ]
            },
            {
                "title" : "Bubble Tea's",
                "products" : [
                    {
                        "title" : "Yaban Mersinli Bubble Tea",
                        "image" : "menuphotos/144.jpg",
                        "price" : "80 ₺"
                    },
                    {
                        "title" : "Şeftali Bubble Tea",
                        "image" : "menuphotos/144.jpg",
                        "price" : "80 ₺"
                    },
                    {
                        "title" : "Coconut Milk",
                        "image" : "menuphotos/144.jpg",
                        "price" : "80 ₺"
                    },
                    {
                        "title" : "Cooler Lime",
                        "image" : "menuphotos/144.jpg",
                        "price" : "80 ₺"
                    }
                ]
            }
        ]
    }
]